ucompress/__init__.py
ucompress/experiments/__init__.py
ucompress/experiments/cheb.py
ucompress/experiments/displacement_controlled.py
ucompress/experiments/experiment.py
ucompress/experiments/force_controlled.py
ucompress/experiments/hydration.py
ucompress/experiments/solution.py
ucompress/fitting/__init__.py
ucompress/fitting/chi_calculator.py
ucompress/fitting/porosity_calculator.py
ucompress/fitting/stress_strain.py
ucompress/models/__init__.py
ucompress/models/base_models.py
ucompress/models/mechanics/__init__.py
ucompress/models/mechanics/base_mechanics.py
ucompress/models/mechanics/fibre_network.py
ucompress/models/mechanics/fibre_recruitment.py
ucompress/models/mechanics/fibre_reinforced.py
ucompress/models/mechanics/fibre_reinforced_invariants.py
ucompress/models/mechanics/fibre_reinforced_quad.py
ucompress/models/mechanics/neo_hookean.py
ucompress/models/osmosis/__init__.py
ucompress/models/osmosis/base_osmosis.py
ucompress/models/osmosis/flory_huggins.py
ucompress/models/osmosis/no_osmosis.py
ucompress/models/permeability/__init__.py
ucompress/models/permeability/base_permeability.py
ucompress/models/permeability/constant.py
ucompress/models/permeability/holmes_mow.py
ucompress/models/permeability/kozeny_carman.py
ucompress/parameters/__init__.py
ucompress/parameters/base_parameters.py
ucompress/parameters/example_parameters.py
ucompress-1.0.0.dist-info/licenses/LICENSE.txt
ucompress-1.0.0.dist-info/METADATA
ucompress-1.0.0.dist-info/WHEEL
ucompress-1.0.0.dist-info/top_level.txt
ucompress-1.0.0.dist-info/RECORD
