Metadata-Version: 2.4
Name: ucompress
Version: 1.0.0
Summary: Simulates the unconfined compression of a poroelastic material
Author-email: Matthew Hennessy <matthew.hennessy@bristol.ac.uk>
License:                     GNU GENERAL PUBLIC LICENSE
Project-URL: Homepage, https://github.com/hennessymatt/ucompress.py
Project-URL: Repository, https://github.com/hennessymatt/ucompress.py
Keywords: poroelasticity,biomechanics,solid mechanics,hydrogels
Requires-Python: >=3.8
License-File: LICENSE.txt
Requires-Dist: numpy
Requires-Dist: scipy
Requires-Dist: sympy
Dynamic: license-file
